accounts/__init__.py
accounts/admin.py
accounts/apps.py
accounts/models.py
accounts/serializers.py
accounts/urls.py
accounts/views.py
accounts/migrations/0001_initial.py
accounts/migrations/__init__.py
djangorestaccounts-0.1.2.dist-info/LICENSE.md
djangorestaccounts-0.1.2.dist-info/METADATA
djangorestaccounts-0.1.2.dist-info/WHEEL
djangorestaccounts-0.1.2.dist-info/top_level.txt
djangorestaccounts-0.1.2.dist-info/RECORD
