Metadata-Version: 2.1
Name: djangorestaccounts
Version: 0.1.2
Summary: A reusable Django  Rest Accounts apps built on Django Rest Framework for fast REST development.
Home-page: https://github.com/kumaraditya303/django-rest-accounts
Author: Kumar Aditya
Author-email: rahuladitya303@gmail.com
License: MIT
Platform: UNKNOWN
Classifier: Framework :: Django
Classifier: Programming Language :: Python :: 3.6
Classifier: Programming Language :: Python :: 3.7
Classifier: Programming Language :: Python :: 3.8
Classifier: Topic :: Internet :: WWW/HTTP
Classifier: Topic :: Internet :: WWW/HTTP :: Dynamic Content
Classifier: Topic :: Software Development
Classifier: Topic :: Software Development :: Libraries
Requires-Python: >=3.6
Requires-Dist: Django (>=3.0)
Requires-Dist: djangorestframework (>=3.0)
Requires-Dist: pillow (>=7.2.0)
